pyodesolver/__init__.py
pyodesolver/method_Gauss_Legendre_2.py
pyodesolver/method_Gauss_Legendre_2_Func02_test.py
pyodesolver/method_Gauss_Legendre_2_test.py
pyodesolver/method_RK4.py
pyodesolver/method_RK4_Func02_test.py
pyodesolver/method_RK4_test.py
pyodesolver/method_bdf6.py
pyodesolver/method_bdf6_test.py
pyodesolver/method_explicit_euler.py
pyodesolver/method_explicit_euler_test.py
pyodesolver/method_implicit_euler.py
pyodesolver/method_implicit_euler_test.py
pyodesolver/method_midpointrule.py
pyodesolver/method_midpointrule_test.py
pyodesolver/ode_solver.py
pyodesolver/rhs_function.py
pyodesolver/step_method.py
PyODESolver-0.1.2.dev0.dist-info/LICENSE
PyODESolver-0.1.2.dev0.dist-info/METADATA
PyODESolver-0.1.2.dev0.dist-info/WHEEL
PyODESolver-0.1.2.dev0.dist-info/top_level.txt
PyODESolver-0.1.2.dev0.dist-info/RECORD
