Metadata-Version: 2.1
Name: PyODESolver
Version: 0.1.2.dev0
Summary: A python package to solve first order ODEs
Home-page: https://github.com/Hoeppke/PyODESolver
Author: C. Hoeppke, A. Puiu
Author-email: christoph.hoeppke@maths.ox.ac.uk
License: MIT license
Platform: UNKNOWN
Classifier: Programming Language :: Python :: 3
Classifier: License :: OSI Approved :: MIT License
Classifier: Operating System :: OS Independent
Requires-Dist: numpy
Requires-Dist: matplotlib
Requires-Dist: scipy
